{
    "181297673318563840": {
        "modification_history": {},
        "total_mods": 0
    },
    "267523838106009611": {
        "modification_history": {
            "aspect_of_the_dragons": {
                "from": [
                    4300000,
                    5500000
                ],
                "to": [
                    4100000,
                    4800000
                ]
            },
            "aspect_of_the_end": {
                "from": [
                    160000,
                    215000
                ],
                "to": [
                    130000,
                    160000
                ]
            },
            "crystal_fragment": {
                "from": [
                    14000,
                    16000
                ],
                "to": [
                    15000,
                    20000
                ]
            },
            "enchanted_baked_potato": {
                "from": [
                    65000,
                    75000
                ],
                "to": [
                    80000,
                    100000
                ]
            },
            "enchanted_diamond_block": {
                "from": [
                    204800,
                    204800
                ],
                "to": [
                    204800,
                    204800
                ]
            },
            "enchanted_egg": {
                "from": [
                    4000,
                    5000
                ],
                "to": [
                    2000,
                    8000
                ]
            },
            "enchanted_glowstone": {
                "from": [
                    95000,
                    115000
                ],
                "to": [
                    160000,
                    200000
                ]
            },
            "enchanted_grilled_pork": {
                "from": [
                    250000,
                    400000
                ],
                "to": [
                    400000,
                    450000
                ]
            },
            "enchanted_lava_bucket": {
                "from": [
                    345000,
                    402000
                ],
                "to": [
                    280000,
                    320000
                ]
            },
            "enchanted_redstone_block": {
                "from": [
                    80000,
                    120000
                ],
                "to": [
                    90000,
                    100000
                ]
            },
            "enchanted_sugar_cane": {
                "from": [
                    75000,
                    150000
                ],
                "to": [
                    125000,
                    135000
                ]
            },
            "feather_artifact": {
                "from": [
                    27000,
                    36000
                ],
                "to": [
                    30000,
                    45000
                ]
            },
            "grappling_hook": {
                "from": [
                    1200,
                    2000
                ],
                "to": [
                    6000,
                    8000
                ]
            },
            "hot_potato_book": {
                "from": [
                    60000,
                    80000
                ],
                "to": [
                    70000,
                    100000
                ]
            },
            "jungle_axe": {
                "from": null,
                "to": [
                    1000,
                    2500
                ]
            },
            "old_dragon_fragment": {
                "from": [
                    750,
                    2000
                ],
                "to": [
                    2000,
                    2400
                ]
            },
            "protector_dragon_fragment": {
                "from": [
                    1000,
                    1750
                ],
                "to": [
                    2000,
                    2300
                ]
            },
            "strong_dragon_boots": {
                "from": [
                    950000,
                    1150000
                ],
                "to": [
                    1000000,
                    1300000
                ]
            },
            "strong_dragon_chestplate": {
                "from": [
                    2300000,
                    2600000
                ],
                "to": [
                    1800000,
                    2400000
                ]
            },
            "strong_dragon_fragment": {
                "from": [
                    25000,
                    28000
                ],
                "to": [
                    22000,
                    25000
                ]
            },
            "strong_dragon_helmet": {
                "from": [
                    900000,
                    1050000
                ],
                "to": [
                    700000,
                    800000
                ]
            },
            "strong_dragon_leggings": {
                "from": [
                    1900000,
                    2400000
                ],
                "to": [
                    1600000,
                    2100000
                ]
            },
            "summoning_eye": {
                "from": [
                    545000,
                    620000
                ],
                "to": [
                    550000,
                    700000
                ]
            },
            "super_compactor_3000": {
                "from": [
                    400000,
                    475000
                ],
                "to": [
                    360000,
                    400000
                ]
            },
            "super_enchanted_egg": {
                "from": [
                    500000,
                    820000
                ],
                "to": [
                    500000,
                    600000
                ]
            },
            "superior_dragon_boots": {
                "from": [
                    6900000,
                    7600000
                ],
                "to": [
                    6300000,
                    7000000
                ]
            },
            "superior_dragon_chestplate": {
                "from": [
                    13000000,
                    14000000
                ],
                "to": [
                    13000000,
                    13600000
                ]
            },
            "superior_dragon_fragment": {
                "from": [
                    150000,
                    165000
                ],
                "to": [
                    155000,
                    165000
                ]
            },
            "superior_dragon_helmet": {
                "from": [
                    8500000,
                    9300000
                ],
                "to": [
                    8000000,
                    8500000
                ]
            },
            "superior_dragon_leggings": {
                "from": [
                    11500000,
                    12500000
                ],
                "to": [
                    12100000,
                    12800000
                ]
            },
            "titanic_experience_bottle": {
                "from": [
                    275000,
                    350000
                ],
                "to": [
                    370000,
                    400000
                ]
            },
            "unstable_dragon_fragment": {
                "from": [
                    4500,
                    5500
                ],
                "to": [
                    6000,
                    7000
                ]
            },
            "wise_dragon_fragment": {
                "from": [
                    2500,
                    2500
                ],
                "to": [
                    2000,
                    2500
                ]
            },
            "young_dragon_fragment": {
                "from": [
                    5100,
                    5100
                ],
                "to": [
                    5000,
                    7000
                ]
            }
        },
        "total_mods": 34
    },
    "289122035005652992": {
        "modification_history": {},
        "total_mods": 0
    },
    "298613178601046017": {
        "modification_history": {
            "clay": {
                "from": [
                    3,
                    3
                ],
                "to": [
                    3,
                    3
                ]
            },
            "grand_experience_bottle": {
                "from": [
                    3500,
                    4000
                ],
                "to": [
                    4000,
                    5000
                ]
            },
            "overflux_capacitor": {
                "from": [
                    68000000,
                    80000000
                ],
                "to": [
                    55000000,
                    55000000
                ]
            }
        },
        "total_mods": 4
    },
    "308262271262654464": {
        "modification_history": {
            "beacon_block": {
                "from": null,
                "to": [
                    500000,
                    700000
                ]
            },
            "challenging_rod": {
                "from": null,
                "to": [
                    300000,
                    400000
                ]
            },
            "clay_minion": {
                "from": null,
                "to": [
                    250,
                    250
                ]
            },
            "critical_iii_potion": {
                "from": null,
                "to": [
                    500,
                    2500
                ]
            },
            "critical_iv_potion": {
                "from": null,
                "to": [
                    50000,
                    80000
                ]
            },
            "enchanted_cooked_mutton": {
                "from": null,
                "to": [
                    200000,
                    256000
                ]
            },
            "enchanted_endstone": {
                "from": null,
                "to": [
                    1200,
                    1300
                ]
            },
            "enchanted_lapis_lazuli": {
                "from": [
                    160,
                    160
                ],
                "to": [
                    500,
                    800
                ]
            },
            "enchanted_mutton": {
                "from": null,
                "to": [
                    3000,
                    5000
                ]
            },
            "frozen_chicken": {
                "from": null,
                "to": [
                    200000,
                    200000
                ]
            },
            "game_breaker": {
                "from": null,
                "to": [
                    20000000,
                    50000000
                ]
            },
            "grinch_minion_skin": {
                "from": null,
                "to": [
                    1000,
                    5000
                ]
            },
            "hunk_of_blue_ice": {
                "from": null,
                "to": [
                    15000,
                    15000
                ]
            },
            "hunk_of_ice": {
                "from": null,
                "to": [
                    200,
                    500
                ]
            },
            "lightning_rune_i": {
                "from": null,
                "to": [
                    5000,
                    10000
                ]
            },
            "lightning_rune_ii": {
                "from": null,
                "to": [
                    50000,
                    100000
                ]
            },
            "lightning_rune_iii": {
                "from": [
                    500000,
                    8000000
                ],
                "to": [
                    500000,
                    800000
                ]
            },
            "magic_find_i_potion": {
                "from": null,
                "to": [
                    5000,
                    25000
                ]
            },
            "magic_find_ii_potion": {
                "from": null,
                "to": [
                    500,
                    500
                ]
            },
            "magic_find_iv_potion": {
                "from": null,
                "to": [
                    80000,
                    150000
                ]
            },
            "yeti_rod": {
                "from": null,
                "to": [
                    5000000,
                    5800000
                ]
            }
        },
        "total_mods": 22
    },
    "333214758436208640": {
        "modification_history": {
            "critical_vi": {
                "from": [
                    175000,
                    350000
                ],
                "to": [
                    350000,
                    500000
                ]
            },
            "enchanted_fermented_spider_eye": {
                "from": [
                    90000,
                    115000
                ],
                "to": [
                    110000,
                    130000
                ]
            },
            "enchanted_leather": {
                "from": [
                    8600,
                    10000
                ],
                "to": [
                    10000,
                    15000
                ]
            },
            "ender_artifact": {
                "from": [
                    8500000,
                    9200000
                ],
                "to": [
                    8000000,
                    8000000
                ]
            },
            "hunter_ring": {
                "from": [
                    30000000,
                    39000000
                ],
                "to": [
                    30000000,
                    35000000
                ]
            },
            "snowman_pet": {
                "from": [
                    1000000,
                    1300000
                ],
                "to": [
                    10000000,
                    13000000
                ]
            },
            "wolf_tooth": {
                "from": [
                    487,
                    487
                ],
                "to": [
                    546,
                    546
                ]
            }
        },
        "total_mods": 10
    },
    "339820544851574784": {
        "modification_history": {
            "enchanted_cobblestone": {
                "from": [
                    1920,
                    1920
                ],
                "to": [
                    800,
                    800
                ]
            },
            "enchanted_egg": {
                "from": [
                    10000,
                    15000
                ],
                "to": [
                    4000,
                    5000
                ]
            },
            "epic_pheonix": {
                "from": null,
                "to": [
                    12000000,
                    17000000
                ]
            },
            "farmer_boots": {
                "from": [
                    125000,
                    165000
                ],
                "to": [
                    165000,
                    187000
                ]
            },
            "flying_fish_pet": {
                "from": null,
                "to": [
                    7500000,
                    9000000
                ]
            },
            "legendary_guardian_pet": {
                "from": null,
                "to": [
                    11000000,
                    12000000
                ]
            },
            "legendary_phoenix": {
                "from": null,
                "to": [
                    155000000,
                    155000000
                ]
            },
            "legendary_turtle_pet": {
                "from": [
                    34000000,
                    30000000
                ],
                "to": [
                    30000000,
                    34000000
                ]
            },
            "legendary_wolf_pet": {
                "from": null,
                "to": [
                    7500000,
                    9000000
                ]
            },
            "mastiff_boots": {
                "from": [
                    760000,
                    850000
                ],
                "to": [
                    1100000,
                    1100000
                ]
            },
            "mastiff_chestplate": {
                "from": [
                    2250000,
                    2500000
                ],
                "to": [
                    1250000,
                    1500000
                ]
            },
            "mastiff_crown": {
                "from": [
                    1150000,
                    1150000
                ],
                "to": [
                    11000000,
                    1300000
                ]
            },
            "mastiff_leggings": {
                "from": [
                    1100000,
                    1340000
                ],
                "to": [
                    1450000,
                    1450000
                ]
            },
            "plumbers_sponge": {
                "from": null,
                "to": [
                    50,
                    50
                ]
            },
            "runaans_bow": {
                "from": [
                    650000,
                    950000
                ],
                "to": [
                    810000,
                    920000
                ]
            },
            "super_enchanted_egg": {
                "from": [
                    500000,
                    1200000
                ],
                "to": [
                    500000,
                    820000
                ]
            },
            "tiger": {
                "from": null,
                "to": [
                    30000,
                    150000
                ]
            }
        },
        "total_mods": 19
    },
    "351251469250461697": {
        "modification_history": {
            "enchanted_baked_potato": {
                "from": [
                    80000,
                    95000
                ],
                "to": [
                    65000,
                    75000
                ]
            },
            "enchanted_grilled_pork": {
                "from": [
                    150000,
                    195000
                ],
                "to": [
                    250000,
                    400000
                ]
            },
            "enchanted_raw_chicken": {
                "from": [
                    3906,
                    4688
                ],
                "to": [
                    1562,
                    2066
                ]
            },
            "epic_ender_dragon_pet": {
                "from": null,
                "to": [
                    36800000,
                    39000000
                ]
            },
            "epic_parrot_pet": {
                "from": null,
                "to": [
                    25000000,
                    26000000
                ]
            },
            "epic_turtle_pet": {
                "from": null,
                "to": [
                    600000,
                    600000
                ]
            },
            "hot_potato_book": {
                "from": [
                    85000,
                    97250
                ],
                "to": [
                    60000,
                    80000
                ]
            },
            "legenadry_pigman_pet": {
                "from": null,
                "to": [
                    10000000,
                    14000000
                ]
            },
            "legendary_enderman_pet": {
                "from": null,
                "to": [
                    55000000,
                    62000000
                ]
            },
            "legendary_lion_pet": {
                "from": null,
                "to": [
                    13000000,
                    23000000
                ]
            },
            "legendary_parrot_pet": {
                "from": null,
                "to": [
                    22000000,
                    22000000
                ]
            },
            "legendary_snowman_pet": {
                "from": null,
                "to": [
                    12000000,
                    12000000
                ]
            },
            "legendary_squid_pet": {
                "from": null,
                "to": [
                    14500000,
                    14500000
                ]
            },
            "legendary_turtle_pet": {
                "from": null,
                "to": [
                    34000000,
                    30000000
                ]
            },
            "pigman_sword": {
                "from": [
                    10000000,
                    13500000
                ],
                "to": [
                    6000000,
                    13000000
                ]
            },
            "potion_affinity_artifact": {
                "from": [
                    375000,
                    450000
                ],
                "to": [
                    425000,
                    500000
                ]
            },
            "scorpion_foil": {
                "from": [
                    500000,
                    2000000
                ],
                "to": [
                    500000,
                    5000000
                ]
            },
            "tarantula_boots": {
                "from": [
                    820000,
                    1240000
                ],
                "to": [
                    1150000,
                    2300000
                ]
            },
            "tarantula_helmet": {
                "from": [
                    550000,
                    620000
                ],
                "to": [
                    400000,
                    850000
                ]
            },
            "tarantula_talisman": {
                "from": [
                    8550000,
                    9000000
                ],
                "to": [
                    7150000,
                    7666666
                ]
            },
            "thick_scorpion_foil": {
                "from": [
                    7000000,
                    8000000
                ],
                "to": [
                    5500000,
                    8300000
                ]
            }
        },
        "total_mods": 22
    },
    "390661701046894592": {
        "modification_history": {
            "budget_hopper": {
                "from": [
                    10000,
                    180000
                ],
                "to": [
                    1200,
                    1200
                ]
            },
            "elegant_tuxedo_jacket": {
                "from": null,
                "to": [
                    30000000,
                    30000000
                ]
            },
            "enchanted_baked_potato": {
                "from": [
                    80000,
                    100000
                ],
                "to": [
                    80000,
                    115000
                ]
            },
            "enchanted_clay": {
                "from": [
                    160,
                    160
                ],
                "to": [
                    480,
                    480
                ]
            },
            "enchanted_coal": {
                "from": [
                    545,
                    625
                ],
                "to": [
                    320,
                    320
                ]
            },
            "enchanted_cobblestone": {
                "from": [
                    575,
                    700
                ],
                "to": [
                    1920,
                    1920
                ]
            },
            "enchanted_diamond": {
                "from": [
                    1280,
                    1280
                ],
                "to": [
                    1520,
                    1520
                ]
            },
            "enchanted_feather": {
                "from": [
                    625,
                    1250
                ],
                "to": [
                    487,
                    487
                ]
            },
            "enchanted_flint": {
                "from": [
                    640,
                    640
                ],
                "to": [
                    640,
                    640
                ]
            },
            "enchanted_gold": {
                "from": [
                    960,
                    1165
                ],
                "to": [
                    640,
                    640
                ]
            },
            "enchanted_gunpowder": {
                "from": [
                    640,
                    640
                ],
                "to": [
                    640,
                    640
                ]
            },
            "enchanted_iron": {
                "from": [
                    960,
                    1060
                ],
                "to": [
                    480,
                    480
                ]
            },
            "enchanted_lapis_lazuli": {
                "from": [
                    160,
                    160
                ],
                "to": [
                    160,
                    160
                ]
            },
            "enchanted_potato": {
                "from": [
                    315,
                    625
                ],
                "to": [
                    160,
                    160
                ]
            },
            "enchanted_raw_beef": {
                "from": [
                    640,
                    865
                ],
                "to": [
                    640,
                    640
                ]
            },
            "enchanted_raw_chicken": {
                "from": [
                    1562,
                    2066
                ],
                "to": [
                    3750,
                    3750
                ]
            },
            "enchanted_sponge": {
                "from": [
                    2000,
                    2000
                ],
                "to": [
                    1420,
                    1420
                ]
            },
            "enchanted_sugar_cane": {
                "from": [
                    105000,
                    135000
                ],
                "to": [
                    75000,
                    150000
                ]
            },
            "ender_pearl": {
                "from": [
                    5,
                    5
                ],
                "to": [
                    10,
                    10
                ]
            },
            "hot_potato_book": {
                "from": [
                    85000,
                    110000
                ],
                "to": [
                    85000,
                    97250
                ]
            },
            "large_backpack": {
                "from": [
                    100000,
                    185000
                ],
                "to": [
                    75000,
                    175000
                ]
            },
            "miner_boots": {
                "from": null,
                "to": [
                    650,
                    650
                ]
            },
            "miner_chestplate": {
                "from": null,
                "to": [
                    1420,
                    1420
                ]
            },
            "miner_helmet": {
                "from": null,
                "to": [
                    700,
                    700
                ]
            },
            "miner_leggings": {
                "from": null,
                "to": [
                    1200,
                    1200
                ]
            },
            "polished_pebble": {
                "from": null,
                "to": [
                    500,
                    500
                ]
            },
            "silverfish_pet": {
                "from": null,
                "to": [
                    1000,
                    12500
                ]
            },
            "sponge": {
                "from": null,
                "to": [
                    10,
                    10
                ]
            },
            "technoblade": {
                "from": null,
                "to": [
                    99999999,
                    99999999
                ]
            },
            "unstable_dragon_chestplate": {
                "from": [
                    670000,
                    870000
                ],
                "to": [
                    175000,
                    450000
                ]
            },
            "zombie_heart": {
                "from": [
                    350000,
                    400000
                ],
                "to": [
                    300000,
                    325000
                ]
            }
        },
        "total_mods": 36
    },
    "412046616934088714": {
        "modification_history": {},
        "total_mods": 0
    },
    "420437729696808962": {
        "modification_history": {},
        "total_mods": 0
    },
    "437305878257860608": {
        "modification_history": {
            "aspect_of_the_dragons": {
                "from": [
                    4100000,
                    4800000
                ],
                "to": [
                    4100000,
                    5300000
                ]
            },
            "candy_artifact": {
                "from": null,
                "to": [
                    450000,
                    650000
                ]
            },
            "enchanted_coal_block": {
                "from": [
                    120000,
                    155000
                ],
                "to": [
                    120000,
                    165000
                ]
            },
            "enchanted_lapis_block": {
                "from": [
                    85000,
                    100000
                ],
                "to": [
                    35000,
                    65000
                ]
            },
            "enchanted_lava_bucket": {
                "from": [
                    250000,
                    280000
                ],
                "to": [
                    345000,
                    402000
                ]
            },
            "enchanted_raw_chicken": {
                "from": [
                    640,
                    850
                ],
                "to": [
                    3906,
                    4688
                ]
            },
            "ender_artifact": {
                "from": [
                    6500000,
                    7500000
                ],
                "to": [
                    8500000,
                    9200000
                ]
            },
            "feather_artifact": {
                "from": [
                    230000,
                    310000
                ],
                "to": [
                    27000,
                    36000
                ]
            },
            "fire_talisman": {
                "from": null,
                "to": [
                    30000,
                    50000
                ]
            },
            "jingle_bells": {
                "from": null,
                "to": [
                    30000,
                    85000
                ]
            },
            "leaping_sword": {
                "from": [
                    2000000,
                    2800000
                ],
                "to": [
                    1725000,
                    2300000
                ]
            },
            "legendary_ocelot_pet": {
                "from": null,
                "to": [
                    3000000,
                    4000000
                ]
            },
            "legendary_rabbit_pet": {
                "from": null,
                "to": [
                    2500000,
                    3500000
                ]
            },
            "old_dragon_boots": {
                "from": [
                    150000,
                    200000
                ],
                "to": [
                    100000,
                    115000
                ]
            },
            "old_dragon_chestplate": {
                "from": [
                    400000,
                    500000
                ],
                "to": [
                    87000,
                    160000
                ]
            },
            "old_dragon_fragment": {
                "from": [
                    2000,
                    3000
                ],
                "to": [
                    750,
                    2000
                ]
            },
            "old_dragon_helmet": {
                "from": [
                    120000,
                    150000
                ],
                "to": [
                    100000,
                    115000
                ]
            },
            "old_dragon_leggings": {
                "from": [
                    87000,
                    160000
                ],
                "to": [
                    115000,
                    145000
                ]
            },
            "super_enchanted_egg": {
                "from": [
                    1400000,
                    1500000
                ],
                "to": [
                    500000,
                    1200000
                ]
            },
            "wither_artifact": {
                "from": [
                    9000000,
                    10500000
                ],
                "to": [
                    10500000,
                    11500000
                ]
            }
        },
        "total_mods": 24
    },
    "466769036122783744": {
        "modification_history": {
            "legendary_phoenix_pet": {
                "from": null,
                "to": [
                    1050000,
                    133000000
                ]
            }
        },
        "total_mods": 1
    },
    "497643063020355604": {
        "modification_history": {
            "Cheap_tuxedo_jacket": {
                "from": null,
                "to": [
                    300000,
                    600000
                ]
            },
            "Parrot": {
                "from": null,
                "to": [
                    25000000,
                    30000000
                ]
            },
            "bait_ring": {
                "from": [
                    16000000,
                    18000000
                ],
                "to": [
                    11000000,
                    12000000
                ]
            },
            "cheap_tuxedo_oxfords": {
                "from": null,
                "to": [
                    80000,
                    100000
                ]
            },
            "cheap_tuxedo_pants": {
                "from": null,
                "to": [
                    200000,
                    200000
                ]
            },
            "crystal_fragment": {
                "from": [
                    15000,
                    20000
                ],
                "to": [
                    20000,
                    20000
                ]
            },
            "digested_mosquito": {
                "from": [
                    30000000,
                    32000000
                ],
                "to": [
                    17000000,
                    18000000
                ]
            },
            "enchanted_ink": {
                "from": [
                    30000,
                    40000
                ],
                "to": [
                    30000,
                    30000
                ]
            },
            "fancy_tuxedo_jacket": {
                "from": null,
                "to": [
                    9000000,
                    9500000
                ]
            },
            "fancy_tuxedo_oxfords": {
                "from": [
                    200000,
                    200000
                ],
                "to": [
                    2000000,
                    2000000
                ]
            },
            "fancy_tuxedo_pants": {
                "from": [
                    43000000,
                    43000000
                ],
                "to": [
                    4300000,
                    4300000
                ]
            },
            "golden_tooth": {
                "from": [
                    85000,
                    105000
                ],
                "to": [
                    110000,
                    125000
                ]
            },
            "legendary_chicken_pet": {
                "from": [
                    5500000,
                    6500000
                ],
                "to": [
                    2000000,
                    3000000
                ]
            },
            "pigman": {
                "from": null,
                "to": [
                    11500000,
                    13000000
                ]
            },
            "pigman_sword": {
                "from": [
                    6900000,
                    7600000
                ],
                "to": [
                    10000000,
                    13500000
                ]
            },
            "red_claw_egg": {
                "from": [
                    1000000,
                    1900000
                ],
                "to": [
                    1000000,
                    1500000
                ]
            },
            "scythe_blade": {
                "from": [
                    1700000,
                    2000000
                ],
                "to": [
                    17000000,
                    20000000
                ]
            },
            "skeleton_horse": {
                "from": [
                    5000000,
                    6000000
                ],
                "to": [
                    6000000,
                    7000000
                ]
            },
            "squid": {
                "from": null,
                "to": [
                    6500000,
                    9000000
                ]
            },
            "turtle": {
                "from": null,
                "to": [
                    32000000,
                    32000000
                ]
            }
        },
        "total_mods": 26
    },
    "508337831798636544": {
        "modification_history": {
            "feather_ring": {
                "from": null,
                "to": [
                    1800,
                    5000
                ]
            },
            "feather_talisman": {
                "from": null,
                "to": [
                    160,
                    500
                ]
            },
            "magic_find_iv": {
                "from": null,
                "to": [
                    250000,
                    450000
                ]
            },
            "zombie_ring": {
                "from": null,
                "to": [
                    10000,
                    35000
                ]
            }
        },
        "total_mods": 4
    },
    "508529699098591242": {
        "modification_history": {},
        "total_mods": 0
    },
    "614661627513536526": {
        "modification_history": {},
        "total_mods": 0
    },
    "664325814531391528": {
        "modification_history": {},
        "total_mods": 0
    }
}