{
    "245045878790946816": {
        "modification_history": {
            "scythe_blade": {
                "from": [
                    7500000,
                    8400000
                ],
                "to": [
                    6000000,
                    7000000
                ]
            }
        },
        "total_mods": 3
    },
    "255260842637918208": {
        "modification_history": {
            "rare_combat_exp_boost": {
                "from": [
                    100000,
                    200000
                ],
                "to": [
                    500000,
                    900000
                ]
            }
        },
        "total_mods": 4
    },
    "298613178601046017": {
        "modification_history": {
            "compactor": {
                "from": [
                    5000,
                    7000
                ],
                "to": [
                    6500,
                    7250
                ]
            },
            "ember_rod": {
                "from": [
                    100000,
                    150000
                ],
                "to": [
                    60000,
                    95000
                ]
            },
            "enchanted_cactus_green": {
                "from": [
                    1150,
                    1400
                ],
                "to": [
                    1150,
                    1225
                ]
            },
            "enchanted_cobblestone": {
                "from": [
                    700,
                    700
                ],
                "to": [
                    750,
                    870
                ]
            },
            "enchanted_diamond": {
                "from": [
                    1300,
                    1300
                ],
                "to": [
                    1280,
                    1325
                ]
            },
            "enchanted_glowstone_dust": {
                "from": [
                    530,
                    650
                ],
                "to": [
                    600,
                    625
                ]
            },
            "enchanted_gold": {
                "from": [
                    1650,
                    1750
                ],
                "to": [
                    1800,
                    1875
                ]
            },
            "enchanted_hay_bale": {
                "from": [
                    17000,
                    18000
                ],
                "to": [
                    16000,
                    19000
                ]
            },
            "enchanted_ice": {
                "from": [
                    620,
                    775
                ],
                "to": [
                    700,
                    750
                ]
            },
            "enchanted_iron_block": {
                "from": [
                    160000,
                    168000
                ],
                "to": [
                    170000,
                    175000
                ]
            },
            "enchanted_lapis_lazuli": {
                "from": [
                    700,
                    775
                ],
                "to": [
                    775,
                    850
                ]
            },
            "enchanted_melon": {
                "from": [
                    200,
                    225
                ],
                "to": [
                    220,
                    260
                ]
            },
            "enchanted_potato": {
                "from": [
                    540,
                    700
                ],
                "to": [
                    575,
                    650
                ]
            },
            "enchanted_pumpkin": {
                "from": [
                    650,
                    850
                ],
                "to": [
                    640,
                    660
                ]
            },
            "enchanted_quartz": {
                "from": [
                    1650,
                    1750
                ],
                "to": [
                    1750,
                    1900
                ]
            },
            "enchanted_quartz_block": {
                "from": [
                    275000,
                    290000
                ],
                "to": [
                    300000,
                    330000
                ]
            },
            "ender_bow": {
                "from": [
                    2500,
                    4500
                ],
                "to": [
                    1000,
                    3000
                ]
            },
            "farmer_orb": {
                "from": [
                    140000,
                    200000
                ],
                "to": [
                    100000,
                    200000
                ]
            },
            "farming_talisman": {
                "from": [
                    120,
                    120
                ],
                "to": [
                    25,
                    125
                ]
            },
            "fish_hat": {
                "from": [
                    175,
                    190
                ],
                "to": [
                    20,
                    50
                ]
            },
            "growth_v": {
                "from": [
                    7500,
                    20000
                ],
                "to": [
                    10000,
                    20000
                ]
            },
            "haste_ring": {
                "from": [
                    180000,
                    180000
                ],
                "to": [
                    120000,
                    200000
                ]
            },
            "magical_water_bucket": {
                "from": [
                    7500,
                    7500
                ],
                "to": [
                    40,
                    7500
                ]
            },
            "minion_expander": {
                "from": [
                    5000,
                    20000
                ],
                "to": [
                    5000,
                    25000
                ]
            },
            "strong_dragon_fragment": {
                "from": [
                    15000,
                    16000
                ],
                "to": [
                    16000,
                    17500
                ]
            },
            "strong_dragon_helmet": {
                "from": [
                    475000,
                    600000
                ],
                "to": [
                    500000,
                    750000
                ]
            },
            "summoning_eye": {
                "from": [
                    530000,
                    535000
                ],
                "to": [
                    540000,
                    560000
                ]
            },
            "super_compactor_3000": {
                "from": [
                    510000,
                    540000
                ],
                "to": [
                    520000,
                    550000
                ]
            },
            "tarantula_web": {
                "from": [
                    23,
                    25
                ],
                "to": [
                    25,
                    31
                ]
            },
            "titanic_experience_bottle": {
                "from": [
                    280000,
                    350000
                ],
                "to": [
                    200000,
                    320000
                ]
            },
            "training_dummy": {
                "from": [
                    5000,
                    10000
                ],
                "to": [
                    1000,
                    20000
                ]
            },
            "wolf_talisman": {
                "from": [
                    430000,
                    460000
                ],
                "to": [
                    500000,
                    600000
                ]
            },
            "wolf_tooth": {
                "from": [
                    210,
                    235
                ],
                "to": [
                    210,
                    250
                ]
            }
        },
        "total_mods": 34
    },
    "308262271262654464": {
        "modification_history": {},
        "total_mods": 0
    },
    "310369675987124225": {
        "modification_history": {},
        "total_mods": 0
    },
    "325337387796267019": {
        "modification_history": {
            "bait_ring": {
                "from": [
                    4650000,
                    5000000
                ],
                "to": [
                    5500000,
                    6250000
                ]
            },
            "lvl_1_epic_ender_dragon": {
                "from": [
                    75000000,
                    90000000
                ],
                "to": [
                    67500000,
                    77500000
                ]
            },
            "rare_combat_exp_boost": {
                "from": [
                    500000,
                    900000
                ],
                "to": [
                    675000,
                    800000
                ]
            },
            "reaper_falchion": {
                "from": [
                    3200000,
                    4000000
                ],
                "to": [
                    4500000,
                    5000000
                ]
            },
            "snow_minion_i": {
                "from": [
                    50000,
                    100000
                ],
                "to": [
                    75000,
                    125000
                ]
            },
            "superior_dragon_helmet": {
                "from": [
                    12000000,
                    12000000
                ],
                "to": [
                    11750000,
                    12500000
                ]
            },
            "treecapitator": {
                "from": [
                    2100000,
                    2300000
                ],
                "to": [
                    1800000,
                    2000000
                ]
            },
            "water_hydra_head": {
                "from": [
                    55000,
                    55000
                ],
                "to": [
                    25000,
                    50000
                ]
            }
        },
        "total_mods": 8
    },
    "334763167391416322": {
        "modification_history": {},
        "total_mods": 2
    },
    "347884694408265729": {
        "modification_history": {
            "angler_vi": {
                "from": [
                    150000,
                    200000
                ],
                "to": [
                    120000,
                    200000
                ]
            },
            "enchanted_mutton": {
                "from": [
                    2000,
                    2000
                ],
                "to": [
                    2150,
                    2275
                ]
            },
            "epic_foraging_exp_boost": {
                "from": null,
                "to": [
                    6000000,
                    10000000
                ]
            },
            "luck_of_the_sea_vi": {
                "from": [
                    500000,
                    650000
                ],
                "to": [
                    200000,
                    500000
                ]
            },
            "lvl_1_epic_blaze": {
                "from": [
                    5000000,
                    8000000
                ],
                "to": [
                    10000000,
                    15000000
                ]
            },
            "lvl_1_epic_chicken": {
                "from": null,
                "to": [
                    10000,
                    50000
                ]
            },
            "snow_minion_i": {
                "from": [
                    75000,
                    125000
                ],
                "to": [
                    100000,
                    150000
                ]
            },
            "superior_dragon_chestplate": {
                "from": [
                    17500000,
                    19000000
                ],
                "to": [
                    19000000,
                    20000000
                ]
            },
            "superior_dragon_leggings": {
                "from": [
                    15500000,
                    17000000
                ],
                "to": [
                    16500000,
                    17500000
                ]
            },
            "zombie_ring": {
                "from": [
                    10000,
                    35000
                ],
                "to": [
                    1000,
                    5000
                ]
            }
        },
        "total_mods": 12
    },
    "366232910334001152": {
        "modification_history": {},
        "total_mods": 0
    },
    "383791723945394176": {
        "modification_history": {},
        "total_mods": 2
    },
    "390661701046894592": {
        "modification_history": {},
        "total_mods": 2
    },
    "391726083512467458": {
        "modification_history": {
            "angler_vi": {
                "from": [
                    150000,
                    150000
                ],
                "to": [
                    150000,
                    200000
                ]
            },
            "carrot": {
                "from": [
                    5,
                    5
                ],
                "to": [
                    4,
                    5
                ]
            },
            "caster_vi": {
                "from": [
                    350000,
                    500000
                ],
                "to": [
                    400000,
                    500000
                ]
            },
            "day_crystal": {
                "from": [
                    250000,
                    300000
                ],
                "to": [
                    280000,
                    315000
                ]
            },
            "digested_mosquito": {
                "from": [
                    10000000,
                    13000000
                ],
                "to": [
                    11000000,
                    12000000
                ]
            },
            "enchanted_fermented_spider_eye": {
                "from": [
                    null,
                    null
                ],
                "to": [
                    95000,
                    105000
                ]
            },
            "enchanted_lily_pad": {
                "from": [
                    46000,
                    50000
                ],
                "to": [
                    40000,
                    43000
                ]
            },
            "ender_artifact": {
                "from": [
                    10000000,
                    12000000
                ],
                "to": [
                    11000000,
                    12000000
                ]
            },
            "fish_affinity_talisman": {
                "from": [
                    175000,
                    250000
                ],
                "to": [
                    50000,
                    125000
                ]
            },
            "greater_backpack": {
                "from": [
                    400000,
                    520000
                ],
                "to": [
                    400000,
                    500000
                ]
            },
            "ink_wand": {
                "from": [
                    1150000,
                    1300000
                ],
                "to": [
                    1100000,
                    1250000
                ]
            },
            "lily_pad": {
                "from": [
                    40000,
                    43000
                ],
                "to": [
                    275,
                    300
                ]
            },
            "luck_of_the_sea_vi": {
                "from": [
                    200000,
                    500000
                ],
                "to": [
                    500000,
                    650000
                ]
            },
            "luck_vi": {
                "from": [
                    40000,
                    60000
                ],
                "to": [
                    40000,
                    70000
                ]
            },
            "lvl_100_epic_parrot": {
                "from": [
                    34000000,
                    36000000
                ],
                "to": [
                    32500000,
                    34000000
                ]
            },
            "lvl_1_epic_parrot": {
                "from": [
                    22000000,
                    25000000
                ],
                "to": [
                    23000000,
                    26000000
                ]
            },
            "maddox_batphone": {
                "from": [
                    450000,
                    490000
                ],
                "to": [
                    450000,
                    500000
                ]
            },
            "mosquito_bow": {
                "from": [
                    30000000,
                    38000000
                ],
                "to": [
                    35000000,
                    38000000
                ]
            },
            "night_crystal": {
                "from": [
                    250000,
                    300000
                ],
                "to": [
                    280000,
                    315000
                ]
            },
            "overflux_capacitor": {
                "from": [
                    53500000,
                    58000000
                ],
                "to": [
                    55000000,
                    58000000
                ]
            },
            "overflux_power_orb": {
                "from": [
                    68000000,
                    80000000
                ],
                "to": [
                    72000000,
                    80000000
                ]
            },
            "power_vi": {
                "from": [
                    3500000,
                    4300000
                ],
                "to": [
                    3800000,
                    4200000
                ]
            },
            "reaper_falchion": {
                "from": [
                    4000000,
                    5500000
                ],
                "to": [
                    4000000,
                    5000000
                ]
            },
            "revenant_falchion": {
                "from": [
                    400000,
                    540000
                ],
                "to": [
                    650000,
                    750000
                ]
            },
            "rod_of_champions": {
                "from": [
                    900000,
                    1200000
                ],
                "to": [
                    450000,
                    600000
                ]
            },
            "rod_of_legends": {
                "from": [
                    6000000,
                    7000000
                ],
                "to": [
                    6500000,
                    7000000
                ]
            },
            "scavenger_iv": {
                "from": [
                    15000,
                    30000
                ],
                "to": [
                    40000,
                    70000
                ]
            },
            "shredder": {
                "from": [
                    4200000,
                    5000000
                ],
                "to": [
                    4000000,
                    4500000
                ]
            },
            "snow_minion_i": {
                "from": [
                    160000,
                    225000
                ],
                "to": [
                    50000,
                    100000
                ]
            },
            "snow_minion_xi": {
                "from": [
                    75000,
                    125000
                ],
                "to": [
                    350000,
                    400000
                ]
            },
            "superb_carrot_candy": {
                "from": [
                    2200000,
                    2600000
                ],
                "to": [
                    2400000,
                    2600000
                ]
            },
            "titanic_experience_bottle": {
                "from": [
                    200000,
                    320000
                ],
                "to": [
                    200000,
                    280000
                ]
            },
            "weak_wolf_catalyst": {
                "from": [
                    250000,
                    300000
                ],
                "to": [
                    175000,
                    250000
                ]
            },
            "wise_dragon_fragment": {
                "from": [
                    4250,
                    4500
                ],
                "to": [
                    4200,
                    4500
                ]
            },
            "wise_dragon_leggings": {
                "from": [
                    100000,
                    200000
                ],
                "to": [
                    150000,
                    200000
                ]
            },
            "wolf_ring": {
                "from": [
                    700000,
                    900000
                ],
                "to": [
                    800000,
                    950000
                ]
            },
            "wolf_talisman": {
                "from": [
                    500000,
                    600000
                ],
                "to": [
                    500000,
                    580000
                ]
            }
        },
        "total_mods": 45
    },
    "396545298069061642": {
        "modification_history": {},
        "total_mods": 1
    },
    "406906204309159937": {
        "modification_history": {},
        "total_mods": 0
    },
    "466769036122783744": {
        "modification_history": {
            "test": {
                "from": [
                    1,
                    1
                ],
                "to": [
                    2,
                    2
                ]
            }
        },
        "total_mods": 4
    },
    "523019950072266764": {
        "modification_history": {},
        "total_mods": 0
    },
    "540685105513889793": {
        "modification_history": {},
        "total_mods": 2
    },
    "610172131057074191": {
        "modification_history": {},
        "total_mods": 1
    },
    "614661627513536526": {
        "modification_history": {},
        "total_mods": 0
    },
    "625347543705976852": {
        "modification_history": {},
        "total_mods": 1
    },
    "626467774310383659": {
        "modification_history": {},
        "total_mods": 0
    },
    "640849699297034250": {
        "modification_history": {},
        "total_mods": 0
    },
    "645434212639571971": {
        "modification_history": {
            "blaze_rod": {
                "from": [
                    24,
                    24
                ],
                "to": [
                    20,
                    24
                ]
            },
            "enchanted_blaze_powder": {
                "from": [
                    2615,
                    2695
                ],
                "to": [
                    2720,
                    2935
                ]
            },
            "enchanted_blaze_rod": {
                "from": [
                    435000,
                    455000
                ],
                "to": [
                    470000,
                    485000
                ]
            },
            "enchanted_bread": {
                "from": [
                    50,
                    60
                ],
                "to": [
                    50,
                    60
                ]
            },
            "enchanted_carrot": {
                "from": [
                    550,
                    650
                ],
                "to": [
                    590,
                    625
                ]
            },
            "enchanted_cooked_fish": {
                "from": [
                    700000,
                    730000
                ],
                "to": [
                    600000,
                    650000
                ]
            },
            "enchanted_cooked_mutton": {
                "from": [
                    155000,
                    180000
                ],
                "to": [
                    132000,
                    152500
                ]
            },
            "enchanted_ink_sack": {
                "from": [
                    16000,
                    17000
                ],
                "to": [
                    18500,
                    19500
                ]
            },
            "enchanted_melon": {
                "from": [
                    220,
                    260
                ],
                "to": [
                    200,
                    222
                ]
            },
            "enchanted_mutton": {
                "from": [
                    2150,
                    2275
                ],
                "to": [
                    2160,
                    2260
                ]
            },
            "enchanted_raw_fish": {
                "from": [
                    4000,
                    4500
                ],
                "to": [
                    3700,
                    4200
                ]
            },
            "enchanted_redstone": {
                "from": [
                    1000,
                    1100
                ],
                "to": [
                    1030,
                    1055
                ]
            },
            "enchanted_redstone_block": {
                "from": [
                    155000,
                    165000
                ],
                "to": [
                    166000,
                    170000
                ]
            },
            "enchanted_sponge": {
                "from": [
                    5000,
                    5500
                ],
                "to": [
                    4900,
                    5350
                ]
            },
            "enchanted_sugar": {
                "from": [
                    544,
                    560
                ],
                "to": [
                    535,
                    565
                ]
            },
            "enchanted_sugar_cane": {
                "from": [
                    87000,
                    89000
                ],
                "to": [
                    89500,
                    91100
                ]
            },
            "enchanted_wet_sponge": {
                "from": [
                    170000,
                    190000
                ],
                "to": [
                    185000,
                    210000
                ]
            },
            "ink_sack": {
                "from": [
                    200,
                    200
                ],
                "to": [
                    220,
                    240
                ]
            },
            "mutton": {
                "from": [
                    15,
                    19
                ],
                "to": [
                    19,
                    23
                ]
            },
            "raw_fish": {
                "from": [
                    25,
                    30
                ],
                "to": [
                    21,
                    24
                ]
            },
            "redstone": {
                "from": [
                    8,
                    9
                ],
                "to": [
                    7,
                    8
                ]
            },
            "snow_minion_xi": {
                "from": [
                    300000,
                    400000
                ],
                "to": [
                    300000,
                    400000
                ]
            },
            "sponge": {
                "from": [
                    130,
                    130
                ],
                "to": [
                    110,
                    130
                ]
            },
            "sugar_cane": {
                "from": [
                    4,
                    5
                ],
                "to": [
                    3,
                    5
                ]
            },
            "super_compactor_3000": {
                "from": [
                    520000,
                    550000
                ],
                "to": [
                    555000,
                    560000
                ]
            },
            "wheat": {
                "from": [
                    3,
                    4
                ],
                "to": [
                    11,
                    12
                ]
            }
        },
        "total_mods": 29
    },
    "660041857148911617": {
        "modification_history": {},
        "total_mods": 0
    },
    "664325814531391528": {
        "modification_history": {},
        "total_mods": 0
    }
}